{
    "total": 94,
    "users": {
        "1253342402606010399": {
            "count": 3
        },
        "804277913833701397": {
            "count": 41
        },
        "1400876118587871302": {
            "count": 15
        },
        "623945049629130772": {
            "count": 5
        },
        "987034674167709787": {
            "count": 8
        },
        "421959520898514945": {
            "count": 6
        },
        "533391601452580874": {
            "count": 2
        },
        "734468552903360594": {
            "count": 7
        },
        "992730031891697697": {
            "count": 7
        }
    }
}
